generate_licenses/__init__.py
generate_licenses/generate_licenses.py
generate_licenses-1.2.0.dist-info/LICENSE
generate_licenses-1.2.0.dist-info/METADATA
generate_licenses-1.2.0.dist-info/WHEEL
generate_licenses-1.2.0.dist-info/top_level.txt
generate_licenses-1.2.0.dist-info/RECORD
