Metadata-Version: 2.1
Name: generate-licenses
Version: 1.2.0
Summary: Generate a file containing all (locally found) licenses from your project.
Home-page: https://github.com/prisma-ro/licenses-generator
Author: David Pescariu
Author-email: prisma.ro.official@gmail.com
License: UNKNOWN
Project-URL: Bug Tracker, https://github.com/prisma-ro/licenses-generator/issues
Platform: UNKNOWN
Classifier: Programming Language :: Python :: 3
Classifier: License :: OSI Approved :: Apache Software License
Classifier: Operating System :: OS Independent
Requires-Python: >=3.6
